rrpproxy/__init__.py
rrpproxy/rrpproxy.py
rrpproxy/utils/__init__.py
rrpproxy/utils/populate_domain_list.py
rrpproxy/utils/rrp_proxy_internal_status_exception.py
rrpproxy/utils/rrpproxy_api_down_exception.py
rrpproxy/utils/status_codes.py
tests/__init__.py
tests/test_get_last_updated_domains_with_details.py
tests/test_rrpproxy_add_contact.py
tests/test_rrpproxy_add_domain.py
tests/test_rrpproxy_base.py
tests/test_rrpproxy_call.py
tests/test_rrpproxy_check_contact.py
tests/test_rrpproxy_check_domain.py
tests/test_rrpproxy_check_domain_transfer.py
tests/test_rrpproxy_delete_contact.py
tests/test_rrpproxy_delete_domain.py
tests/test_rrpproxy_get_domain_list_from_account.py
tests/test_rrpproxy_get_domain_with_details.py
tests/test_rrpproxy_get_zone_info.py
tests/test_rrpproxy_init.py
tests/test_rrpproxy_modify_contact.py
tests/test_rrpproxy_modify_domain.py
tests/test_rrpproxy_query_domain_list.py
tests/test_rrpproxy_query_foreign_transfer_list.py
tests/test_rrpproxy_query_transfer_list.py
tests/test_rrpproxy_query_zone_list.py
tests/test_rrpproxy_renew_domain.py
tests/test_rrpproxy_resend_notification.py
tests/test_rrpproxy_response_to_dict.py
tests/test_rrpproxy_set_auth_code.py
tests/test_rrpproxy_set_domain_renewal_mode.py
tests/test_rrpproxy_status_contact.py
tests/test_rrpproxy_status_domain.py
tests/test_rrpproxy_status_domain_transfer.py
tests/test_rrpproxy_trade_domain.py
tests/test_rrpproxy_transfer_domain.py
tests/utils/__init__.py
tests/utils/test_populate_domain_list.py
tests/utils/test_rrp_proxy_internal_status_exception.py
tests/utils/test_rrpproxy_api_down_exception.py
tests/utils/test_status_codes.py
rrpproxy-0.1.6.dist-info/LICENSE
rrpproxy-0.1.6.dist-info/METADATA
rrpproxy-0.1.6.dist-info/WHEEL
rrpproxy-0.1.6.dist-info/top_level.txt
rrpproxy-0.1.6.dist-info/RECORD
