Metadata-Version: 2.1
Name: rrpproxy
Version: 0.1.6
Summary: A python connector for RRP Proxy
Home-page: https://github.com/ByteInternet/rrpproxy
Download-URL: https://github.com/ByteInternet/rrpproxy/archive/20201012.1.tar.gz
Author: Tech
Author-email: tech@byte.nl
Classifier: Intended Audience :: Developers
Classifier: Operating System :: OS Independent
Classifier: Programming Language :: Python
Classifier: Topic :: Internet :: WWW/HTTP
Classifier: Topic :: Internet :: WWW/HTTP :: Dynamic Content
Requires-Python: >=3.4
License-File: LICENSE
